turnt/__init__.py
turnt/__main__.py
turnt/config.py
turnt/run.py
turnt-1.11.0.dist-info/entry_points.txt
turnt-1.11.0.dist-info/LICENSE
turnt-1.11.0.dist-info/WHEEL
turnt-1.11.0.dist-info/METADATA
turnt-1.11.0.dist-info/RECORD
