Metadata-Version: 2.1
Name: turnt
Version: 1.11.0
Summary: Turnt is a simple expect-style testing tool for command-line
Home-page: https://github.com/cucapra/turnt
Author: Adrian Sampson
Author-email: asampson@cs.cornell.edu
Requires-Python: >=3.6
Requires-Dist: click != 8.1.4
Requires-Dist: tomli >= 1.1.0 ; python_version < "3.11"
